{
  "qa": [
    {
      "question": "On average how many people are killed at work each year in the UK?",
      "answers": [
        120,
        220,
        320
      ],
      "answerIndex": 0
    },
    {
      "question": "Which of the following are true?",
      "answers": [
        "Usually, the higher the risk level, the more action needs to be taken",
        "There's only one way to carry out a risk assessment",
        "Risk action levels are the same for every company"
      ],
      "answerIndex": 2
    }
  ]
}